{
  "$schema": "http://json-schema.org/draft-04/schema#",
  "type": "object",
  "required": [
    "code",
    "message",
    "data"
  ],
  "properties": {
    "code": {
      "type": "number",
      "description": "状态码",
      "mock": {
        "mock": "200"
      }
    },
    "message": {
      "type": "string",
      "mock": {
        "mock": "success"
      }
    },
    "data": {
      "type": "object",
      "required": [
        "formObject"
      ],
      "properties": {
        "formObject": {
          "type": "object",
          "required": [],
          "properties": {}
        }
      }
    }
  }
}